mensura/__init__.py
mensura/base.py
mensura/conversions.py
mensura/exceptions.py
mensura-0.2.2.dist-info/licenses/LICENSE
mensura-0.2.2.dist-info/METADATA
mensura-0.2.2.dist-info/WHEEL
mensura-0.2.2.dist-info/top_level.txt
mensura-0.2.2.dist-info/RECORD
