Metadata-Version: 2.4
Name: mensura
Version: 0.2.2
Summary: Unit converter using graph-based methods
Requires-Python: >=3.13
License-File: LICENSE
Dynamic: license-file
